silkie/__init__.py
silkie/__main__.py
silkie/cli.py
silkie/definitions.py
silkie/options.py
silkie/utils.py
silkie-1.0.7.dist-info/LICENSE
silkie-1.0.7.dist-info/METADATA
silkie-1.0.7.dist-info/WHEEL
silkie-1.0.7.dist-info/entry_points.txt
silkie-1.0.7.dist-info/top_level.txt
silkie-1.0.7.dist-info/RECORD
