Metadata-Version: 2.1
Name: silkie
Version: 1.0.7
Summary: Static site generator with the smoothness of silk
Home-page: https://github.com/oliver-pham/silkie
Author: Oliver Pham
Author-email: oliverptpham@gmail.com
License: UNKNOWN
Project-URL: Bug Tracker, https://github.com/oliver-pham/silkie/issues
Platform: UNKNOWN
Classifier: Programming Language :: Python :: 3
Classifier: License :: OSI Approved :: MIT License
Classifier: Operating System :: OS Independent
Requires-Python: >=3.9
License-File: LICENSE
Requires-Dist: click (>=8.0.0)
Requires-Dist: markdown (>=3.3.0)
Requires-Dist: yattag (>=1.14.0)
Requires-Dist: python-frontmatter (>=1.0.0)
